Workbook

Sheet Feature Matrix
A1: Feature Matrix — who gets what
A2: Which section each planned feature belongs to. Use the Yes/No dropdowns to change a cell; colours and the Gantt update automatically.
A4: # | B4: Phase | C4: Feature | D4: Guest / Non-logged-in | E4: Logged-in User | F4: Admin Utility
A5: Phase 0 — Foundation
A6: 1 | B6: Phase 0 — Foundation | C6: Design Review | D6: Yes | E6: Yes | F6: Yes
A7: 2 | B7: Phase 0 — Foundation | C7: Cloud Architecture & Platform Setup | D7: Yes | E7: Yes | F7: Yes
A8: 3 | B8: Phase 0 — Foundation | C8: Data Migration Planning | D8: No | E8: Yes | F8: Yes
A9: 4 | B9: Phase 0 — Foundation | C9: Payment Provider Setup | D9: Yes | E9: Yes | F9: Yes
A10: 5 | B10: Phase 0 — Foundation | C10: App Delivery Platform Enrollment | D10: Yes | E10: Yes | F10: No
A11: 6 | B11: Phase 0 — Foundation | C11: Auth, Identity & RBAC | D11: Yes | E11: Yes | F11: Yes
A12: Phase 1 — v1.0
A13: 7 | B13: Phase 1 — v1.0 | C13: Home & Panchang | D13: Yes | E13: Yes | F13: Yes
A14: 8 | B14: Phase 1 — v1.0 | C14: Calendar & Events | D14: Yes | E14: Yes | F14: Yes
A15: 9 | B15: Phase 1 — v1.0 | C15: Content & Newsletter | D15: Yes | E15: Yes | F15: Yes
A16: 10 | B16: Phase 1 — v1.0 | C16: Payments & Billing Infrastructure | D16: Yes | E16: Yes | F16: Yes
A17: 11 | B17: Phase 1 — v1.0 | C17: Admin — Shell, Dashboards & Members | D17: No | E17: No | F17: Yes
A18: 12 | B18: Phase 1 — v1.0 | C18: Donations & Causes | D18: Yes | E18: Yes | F18: Yes
A19: 13 | B19: Phase 1 — v1.0 | C19: Recurring Giving & Subscriptions | D19: No | E19: Yes | F19: Yes
A20: 14 | B20: Phase 1 — v1.0 | C20: Membership, Family & Dues | D20: Yes | E20: Yes | F20: Yes
A21: 15 | B21: Phase 1 — v1.0 | C21: Sponsorships & Religious Calendar | D21: No | E21: Yes | F21: Yes
A22: 16 | B22: Phase 1 — v1.0 | C22: Community Feed & Moderation | D22: No | E22: Yes | F22: Yes
A23: 17 | B23: Phase 1 — v1.0 | C23: Notifications & Messaging | D23: No | E23: Yes | F23: Yes
A24: 18 | B24: Phase 1 — v1.0 | C24: Pathshala | D24: No | E24: Yes | F24: Yes
... A31: 25 | B31: Phase 1 — v1.0 | C31: Store & Launch Readiness | D31: Yes | E31: Yes | F31: No
A32: Phase 2 — v1.5
A33: 26 | B33: Phase 2 — v1.5 | C33: Governance & Documents | D33: No | E33: Yes | F33: Yes
A34: 27 | B34: Phase 2 — v1.5 | C34: Library, Jinvani & Lectures | D34: Yes | E34: Yes | F34: Yes
A35: 28 | B35: Phase 2 — v1.5 | C35: Directory, Travel & Facility Booking | D35: No | E35: Yes | F35: Yes
A36: 29 | B36: Phase 2 — v1.5 | C36: Recognition Programs | D36: Yes | E36: Yes | F36: Yes
A37: 30 | B37: Phase 2 — v1.5 | C37: Youth & YJA | D37: No | E37: Yes | F37: Yes
A38: 31 | B38: Phase 2 — v1.5 | C38: Past Events & Gallery | D38: Yes | E38: Yes | F38: Yes
A39: 32 | B39: Phase 2 — v1.5 | C39: Reports & Analytics v2 | D39: No | E39: No | F39: Yes
A40: 33 | B40: Phase 2 — v1.5 | C40: Hindi & Gujarati Localization | D40: Yes | E40: Yes | F40: Yes
A41: 34 | B41: Phase 2 — v1.5 | C41: v1.5 Hardening & Release | D41: Yes | E41: Yes | F41: Yes
A42: Phase 3 — v2.0
A43: 35 | B43: Phase 3 — v2.0 | C43: Jain Philosophy Module | D43: Yes | E43: Yes | F43: Yes
A44: 36 | B44: Phase 3 — v2.0 | C44: JCA Cares | D44: No | E44: Yes | F44: Yes
A45: 37 | B45: Phase 3 — v2.0 | C45: v2.0 Hardening & Release | D45: Yes | E45: Yes | F45: Yes
A46: 38 | B46: Phase 3 — v2.0 | C46: AI Chat (contingent workstream) | D46: No | E46: Yes | F46: Yes
C47: Features with access (Yes) | D47: =COUNTIF(D6:D46,"Yes") | E47: =COUNTIF(E6:E46,"Yes") | F47: =COUNTIF(F6:F46,"Yes")

Sheet Gantt
A1: Gantt — feature timeline
A2: Edit the yellow Start / End cells (or the Project start) and the bars redraw. Dates follow the delivery plan (Phase 0: 5-16 Oct; Phases 1-3 overlap within 18 Oct - 15 Jan). Overtype any date to re-plan.
B3: Project start | C3: 46300
I5: =TEXT(I6,"mmm yy") | J5: =IF(MONTH(J6)<>MONTH(I6),TEXT(J6,"mmm yy"),"") | K5: =IF(MONTH(K6)<>MONTH(J6),TEXT(K6,"mmm yy"),"") | L5: =IF(MONTH(L6)<>MONTH(K6),TEXT(L6,"mmm yy"),"") | M5: =IF(MONTH(M6)<>MONTH(L6),TEXT(M6,"mmm yy"),"") | N5: =IF(MONTH(N6)<>MONTH(M6),TEXT(N6,"mmm yy"),"") | O5: =IF(MONTH(O6)<>MONTH(N6),TEXT(O6,"mmm yy"),"") | P5: =IF(MONTH(P6)<>MONTH(O6),TEXT(P6,"mmm yy"),"") | Q5: =IF(MONTH(Q6)<>MONTH(P6),TEXT(Q6,"mmm yy"),"") | ... DH5: =IF(MONTH(DH6)<>MONTH(DG6),TEXT(DH6,"mmm yy"),"")
H6: Week of → | I6: =$C$3 | J6: =I6+7 | K6: =J6+7 | L6: =K6+7 | M6: =L6+7 | N6: =M6+7 | O6: =N6+7 | P6: =O6+7 | Q6: =P6+7 | ... DH6: =DG6+7
A7: Phase | B7: Feature | C7: Guest | D7: Logged-in | E7: Admin | F7: Start | G7: End | H7: Weeks | I7: W1 | J7: W2 | K7: W3 | L7: W4 | M7: W5 | N7: W6 | O7: W7 | P7: W8 | Q7: W9 | R7: W10 | S7: W11 | T7: W12 | U7: W13 | V7: W14 | W7: W15 | X7: W16 | Y7: W17 | Z7: W18 | AA7: W19 | AB7: W20 | AC7: W21 | AD7: W22 | AE7: W23 | AF7: W24 | AG7: W25 | AH7: W26 | AI7: W27 | AJ7: W28 | AK7: W29 | AL7: W30 | AM7: W31 | AN7: W32 | AO7: W33 | AP7: W34 | AQ7: W35 | AR7: W36 | AS7: W37 | AT7: W38 | AU7: W39 | AV7: W40 | AW7: W41 | AX7: W42 | AY7: W43 | AZ7: W44 | BA7: W45 | BB7: W46 | BC7: W47 | BD7: W48 | BE7: W49 | BF7: W50 | BG7: W51 | BH7: W52 | BI7: W53 | BJ7: W54 | BK7: W55 | BL7: W56 | BM7: W57 | BN7: W58 | BO7: W59 | BP7: W60 | BQ7: W61 | BR7: W62 | BS7: W63 | BT7: W64 | BU7: W65 | BV7: W66 | BW7: W67 | BX7: W68 | BY7: W69 | BZ7: W70 | CA7: W71 | CB7: W72 | CC7: W73 | CD7: W74 | CE7: W75 | CF7: W76 | CG7: W77 | CH7: W78 | CI7: W79 | CJ7: W80 | CK7: W81 | CL7: W82 | CM7: W83 | CN7: W84 | CO7: W85 | CP7: W86 | CQ7: W87 | CR7: W88 | CS7: W89 | CT7: W90 | CU7: W91 | CV7: W92 | CW7: W93 | CX7: W94 | CY7: W95 | CZ7: W96 | DA7: W97 | DB7: W98 | DC7: W99 | DD7: W100 | DE7: W101 | DF7: W102 | DG7: W103 | DH7: W104
A8: Phase 0 — Foundation | F8: =MIN(F9:F14) | G8: =MAX(G9:G14) | H8: =ROUNDUP((G8-F8+1)/7,0)
A9: ='Feature Matrix'!B6 | B9: ='Feature Matrix'!C6 | C9: =IF('Feature Matrix'!D6="Yes","Y","N") | D9: =IF('Feature Matrix'!E6="Yes","Y","N") | E9: =IF('Feature Matrix'!F6="Yes","Y","N") | F9: 46300 | G9: 46311 | H9: =ROUNDUP((G9-F9+1)/7,0)
A10: ='Feature Matrix'!B7 | B10: ='Feature Matrix'!C7 | C10: =IF('Feature Matrix'!D7="Yes","Y","N") | D10: =IF('Feature Matrix'!E7="Yes","Y","N") | E10: =IF('Feature Matrix'!F7="Yes","Y","N") | F10: 46300 | G10: 46311 | H10: =ROUNDUP((G10-F10+1)/7,0)
A11: ='Feature Matrix'!B8 | B11: ='Feature Matrix'!C8 | C11: =IF('Feature Matrix'!D8="Yes","Y","N") | D11: =IF('Feature Matrix'!E8="Yes","Y","N") | E11: =IF('Feature Matrix'!F8="Yes","Y","N") | F11: 46300 | G11: 46311 | H11: =ROUNDUP((G11-F11+1)/7,0)
A12: ='Feature Matrix'!B9 | B12: ='Feature Matrix'!C9 | C12: =IF('Feature Matrix'!D9="Yes","Y","N") | D12: =IF('Feature Matrix'!E9="Yes","Y","N") | E12: =IF('Feature Matrix'!F9="Yes","Y","N") | F12: 46300 | G12: 46311 | H12: =ROUNDUP((G12-F12+1)/7,0)
A13: ='Feature Matrix'!B10 | B13: ='Feature Matrix'!C10 | C13: =IF('Feature Matrix'!D10="Yes","Y","N") | D13: =IF('Feature Matrix'!E10="Yes","Y","N") | E13: =IF('Feature Matrix'!F10="Yes","Y","N") | F13: 46300 | G13: 46311 | H13: =ROUNDUP((G13-F13+1)/7,0)
A14: ='Feature Matrix'!B11 | B14: ='Feature Matrix'!C11 | C14: =IF('Feature Matrix'!D11="Yes","Y","N") | D14: =IF('Feature Matrix'!E11="Yes","Y","N") | E14: =IF('Feature Matrix'!F11="Yes","Y","N") | F14: 46300 | G14: 46311 | H14: =ROUNDUP((G14-F14+1)/7,0)
A15: Phase 1 — v1.0 | F15: =MIN(F16:F34) | G15: =MAX(G16:G34) | H15: =ROUNDUP((G15-F15+1)/7,0)
A16: ='Feature Matrix'!B13 | B16: ='Feature Matrix'!C13 | C16: =IF('Feature Matrix'!D13="Yes","Y","N") | D16: =IF('Feature Matrix'!E13="Yes","Y","N") | E16: =IF('Feature Matrix'!F13="Yes","Y","N") | F16: 46313 | G16: 46340 | H16: =ROUNDUP((G16-F16+1)/7,0)
A17: ='Feature Matrix'!B14 | B17: ='Feature Matrix'!C14 | C17: =IF('Feature Matrix'!D14="Yes","Y","N") | D17: =IF('Feature Matrix'!E14="Yes","Y","N") | E17: =IF('Feature Matrix'!F14="Yes","Y","N") | F17: 46313 | G17: 46333 | H17: =ROUNDUP((G17-F17+1)/7,0)
A18: ='Feature Matrix'!B15 | B18: ='Feature Matrix'!C15 | C18: =IF('Feature Matrix'!D15="Yes","Y","N") | D18: =IF('Feature Matrix'!E15="Yes","Y","N") | E18: =IF('Feature Matrix'!F15="Yes","Y","N") | F18: 46320 | G18: 46340 | H18: =ROUNDUP((G18-F18+1)/7,0)
A19: ='Feature Matrix'!B16 | B19: ='Feature Matrix'!C16 | C19: =IF('Feature Matrix'!D16="Yes","Y","N") | D19: =IF('Feature Matrix'!E16="Yes","Y","N") | E19: =IF('Feature Matrix'!F16="Yes","Y","N") | F19: 46313 | G19: 46340 | H19: =ROUNDUP((G19-F19+1)/7,0)
A20: ='Feature Matrix'!B17 | B20: ='Feature Matrix'!C17 | C20: =IF('Feature Matrix'!D17="Yes","Y","N") | D20: =IF('Feature Matrix'!E17="Yes","Y","N") | E20: =IF('Feature Matrix'!F17="Yes","Y","N") | F20: 46313 | G20: 46347 | H20: =ROUNDUP((G20-F20+1)/7,0)
A21: ='Feature Matrix'!B18 | B21: ='Feature Matrix'!C18 | C21: =IF('Feature Matrix'!D18="Yes","Y","N") | D21: =IF('Feature Matrix'!E18="Yes","Y","N") | E21: =IF('Feature Matrix'!F18="Yes","Y","N") | F21: 46334 | G21: 46361 | H21: =ROUNDUP((G21-F21+1)/7,0)
A22: ='Feature Matrix'!B19 | B22: ='Feature Matrix'!C19 | C22: =IF('Feature Matrix'!D19="Yes","Y","N") | D22: =IF('Feature Matrix'!E19="Yes","Y","N") | E22: =IF('Feature Matrix'!F19="Yes","Y","N") | F22: 46341 | G22: 46368 | H22: =ROUNDUP((G22-F22+1)/7,0)
A23: ='Feature Matrix'!B20 | B23: ='Feature Matrix'!C20 | C23: =IF('Feature Matrix'!D20="Yes","Y","N") | D23: =IF('Feature Matrix'!E20="Yes","Y","N") | E23: =IF('Feature Matrix'!F20="Yes","Y","N") | F23: 46334 | G23: 46361 | H23: =ROUNDUP((G23-F23+1)/7,0)
A24: ='Feature Matrix'!B21 | B24: ='Feature Matrix'!C21 | C24: =IF('Feature Matrix'!D21="Yes","Y","N") | D24: =IF('Feature Matrix'!E21="Yes","Y","N") | E24: =IF('Feature Matrix'!F21="Yes","Y","N") | F24: 46341 | G24: 46368 | H24: =ROUNDUP((G24-F24+1)/7,0)
A25: ='Feature Matrix'!B22 | B25: ='Feature Matrix'!C22 | C25: =IF('Feature Matrix'!D22="Yes","Y","N") | D25: =IF('Feature Matrix'!E22="Yes","Y","N") | E25: =IF('Feature Matrix'!F22="Yes","Y","N") | F25: 46341 | G25: 46375 | H25: =ROUNDUP((G25-F25+1)/7,0)
A26: ='Feature Matrix'!B23 | B26: ='Feature Matrix'!C23 | C26: =IF('Feature Matrix'!D23="Yes","Y","N") | D26: =IF('Feature Matrix'!E23="Yes","Y","N") | E26: =IF('Feature Matrix'!F23="Yes","Y","N") | F26: 46334 | G26: 46361 | H26: =ROUNDUP((G26-F26+1)/7,0)
A27: ='Feature Matrix'!B24 | B27: ='Feature Matrix'!C24 | C27: =IF('Feature Matrix'!D24="Yes","Y","N") | D27: =IF('Feature Matrix'!E24="Yes","Y","N") | E27: =IF('Feature Matrix'!F24="Yes","Y","N") | F27: 46348 | G27: 46375 | H27: =ROUNDUP((G27-F27+1)/7,0)
... A34: ='Feature Matrix'!B31 | B34: ='Feature Matrix'!C31 | C34: =IF('Feature Matrix'!D31="Yes","Y","N") | D34: =IF('Feature Matrix'!E31="Yes","Y","N") | E34: =IF('Feature Matrix'!F31="Yes","Y","N") | F34: 46376 | G34: 46402 | H34: =ROUNDUP((G34-F34+1)/7,0)
A35: Phase 2 — v1.5 | F35: =MIN(F36:F44) | G35: =MAX(G36:G44) | H35: =ROUNDUP((G35-F35+1)/7,0)
A36: ='Feature Matrix'!B33 | B36: ='Feature Matrix'!C33 | C36: =IF('Feature Matrix'!D33="Yes","Y","N") | D36: =IF('Feature Matrix'!E33="Yes","Y","N") | E36: =IF('Feature Matrix'!F33="Yes","Y","N") | F36: 46348 | G36: 46368 | H36: =ROUNDUP((G36-F36+1)/7,0)
A37: ='Feature Matrix'!B34 | B37: ='Feature Matrix'!C34 | C37: =IF('Feature Matrix'!D34="Yes","Y","N") | D37: =IF('Feature Matrix'!E34="Yes","Y","N") | E37: =IF('Feature Matrix'!F34="Yes","Y","N") | F37: 46355 | G37: 46375 | H37: =ROUNDUP((G37-F37+1)/7,0)
A38: ='Feature Matrix'!B35 | B38: ='Feature Matrix'!C35 | C38: =IF('Feature Matrix'!D35="Yes","Y","N") | D38: =IF('Feature Matrix'!E35="Yes","Y","N") | E38: =IF('Feature Matrix'!F35="Yes","Y","N") | F38: 46362 | G38: 46382 | H38: =ROUNDUP((G38-F38+1)/7,0)
A39: ='Feature Matrix'!B36 | B39: ='Feature Matrix'!C36 | C39: =IF('Feature Matrix'!D36="Yes","Y","N") | D39: =IF('Feature Matrix'!E36="Yes","Y","N") | E39: =IF('Feature Matrix'!F36="Yes","Y","N") | F39: 46362 | G39: 46375 | H39: =ROUNDUP((G39-F39+1)/7,0)
A40: ='Feature Matrix'!B37 | B40: ='Feature Matrix'!C37 | C40: =IF('Feature Matrix'!D37="Yes","Y","N") | D40: =IF('Feature Matrix'!E37="Yes","Y","N") | E40: =IF('Feature Matrix'!F37="Yes","Y","N") | F40: 46369 | G40: 46382 | H40: =ROUNDUP((G40-F40+1)/7,0)
A41: ='Feature Matrix'!B38 | B41: ='Feature Matrix'!C38 | C41: =IF('Feature Matrix'!D38="Yes","Y","N") | D41: =IF('Feature Matrix'!E38="Yes","Y","N") | E41: =IF('Feature Matrix'!F38="Yes","Y","N") | F41: 46355 | G41: 46368 | H41: =ROUNDUP((G41-F41+1)/7,0)
A42: ='Feature Matrix'!B39 | B42: ='Feature Matrix'!C39 | C42: =IF('Feature Matrix'!D39="Yes","Y","N") | D42: =IF('Feature Matrix'!E39="Yes","Y","N") | E42: =IF('Feature Matrix'!F39="Yes","Y","N") | F42: 46369 | G42: 46389 | H42: =ROUNDUP((G42-F42+1)/7,0)
A43: ='Feature Matrix'!B40 | B43: ='Feature Matrix'!C40 | C43: =IF('Feature Matrix'!D40="Yes","Y","N") | D43: =IF('Feature Matrix'!E40="Yes","Y","N") | E43: =IF('Feature Matrix'!F40="Yes","Y","N") | F43: 46376 | G43: 46395 | H43: =ROUNDUP((G43-F43+1)/7,0)
A44: ='Feature Matrix'!B41 | B44: ='Feature Matrix'!C41 | C44: =IF('Feature Matrix'!D41="Yes","Y","N") | D44: =IF('Feature Matrix'!E41="Yes","Y","N") | E44: =IF('Feature Matrix'!F41="Yes","Y","N") | F44: 46383 | G44: 46402 | H44: =ROUNDUP((G44-F44+1)/7,0)
A45: Phase 3 — v2.0 | F45: =MIN(F46:F49) | G45: =MAX(G46:G49) | H45: =ROUNDUP((G45-F45+1)/7,0)
A46: ='Feature Matrix'!B43 | B46: ='Feature Matrix'!C43 | C46: =IF('Feature Matrix'!D43="Yes","Y","N") | D46: =IF('Feature Matrix'!E43="Yes","Y","N") | E46: =IF('Feature Matrix'!F43="Yes","Y","N") | F46: 46369 | G46: 46389 | H46: =ROUNDUP((G46-F46+1)/7,0)
A47: ='Feature Matrix'!B44 | B47: ='Feature Matrix'!C44 | C47: =IF('Feature Matrix'!D44="Yes","Y","N") | D47: =IF('Feature Matrix'!E44="Yes","Y","N") | E47: =IF('Feature Matrix'!F44="Yes","Y","N") | F47: 46376 | G47: 46395 | H47: =ROUNDUP((G47-F47+1)/7,0)
A48: ='Feature Matrix'!B45 | B48: ='Feature Matrix'!C45 | C48: =IF('Feature Matrix'!D45="Yes","Y","N") | D48: =IF('Feature Matrix'!E45="Yes","Y","N") | E48: =IF('Feature Matrix'!F45="Yes","Y","N") | F48: 46390 | G48: 46402 | H48: =ROUNDUP((G48-F48+1)/7,0)
A49: ='Feature Matrix'!B46 | B49: ='Feature Matrix'!C46 | C49: =IF('Feature Matrix'!D46="Yes","Y","N") | D49: =IF('Feature Matrix'!E46="Yes","Y","N") | E49: =IF('Feature Matrix'!F46="Yes","Y","N") | F49: 46376 | G49: 46402 | H49: =ROUNDUP((G49-F49+1)/7,0)

Sheet Summary
A1: JCA Platform — Build Plan (Management View)
A2: User stories grouped by phase and module. Timeline, sequencing, and sprint mapping are intentionally left out of this view and will be added once this plan is reviewed and finalized. See the companion detailed workbook for the full developer-facing breakdown (acceptance criteria, subtasks, priority, complexity, sprint plan, schema, and API map).
A4: Phase | B4: Goal | C4: Modules in This Phase | D4: Stories
A5: Phase 0 — Foundation | B5: Designs reviewed and approved, design system locked, skeletons deployed, auth working — gates all feature work per RFP §4.1.1. | C5: Design Review, Cloud Architecture & Platform Setup, Data Migration Planning, Payment Provider Setup, App Delivery Platform Enrollment, Auth, Identity & RBAC | D5: 41
A6: Phase 1 — v1.0 (initial launch) | B6: Every P1 feature live on iOS, Android, Web, and Admin. App Store + Play Store approved. Public web launched. RFP §4.1. | C6: Home & Panchang, Calendar & Events, Content & Newsletter, Payments & Billing Infrastructure, Admin — Shell, Dashboards & Members, Donations & Causes, Recurring Giving & Subscriptions, Membership, Family & Dues, Sponsorships & Religious Calendar, Community Feed & Moderation, Notifications & Messaging, Pathshala, Volunteers & Seva, Live Darshan, Admin — Governance & Operations, Public Web & SEO, Localization & Accessibility, Security, Testing & QA, Store & Launch Readiness | D6: 107
A7: Phase 2 — v1.5 (should-have follow-on release) | B7: Member-gated content, governance transparency, richer educational resources. Hindi/Gujarati fully populated. RFP §4.2. | C7: Governance & Documents, Library, Jinvani & Lectures, Directory, Travel & Facility Booking, Recognition Programs, Youth & YJA, Past Events & Gallery, Reports & Analytics v2, Hindi & Gujarati Localization, v1.5 Hardening & Release | D7: 34
A8: Phase 3 — v2.0 (nice-to-have and contingent) | B8: Educational depth and intelligent assistance. Contingent on Phase 1 and Phase 2 acceptance gates. RFP §4.3. | C8: Jain Philosophy Module, JCA Cares, v2.0 Hardening & Release, AI Chat (contingent workstream) | D8: 12
A10: Fixed technology decisions reflected throughout this plan: a single Expo codebase builds the Web, iOS, and Android UI from one source; Payload CMS is the admin utility and content layer (the admin can edit almost everything, including landing-page content, from one place); FastAPI is the backend API. See the Tech Decisions sheet for the full rationale.

Sheet Tech Decisions
A1: Tech Decisions
A2: What we're building on, why, and what the trade-off is.
A4: Decision | B4: Fixed by User | C4: Options Considered | D4: Why This / Risk & Mitigation | E4: Recommendation
A5: Unified UI framework — Web & App | B5: Yes | C5: Expo (Router + React Native Web), one codebase for iOS/Android/Web · Previous approach: separate Next.js web app + React Native mobile app | D5: User has directed one Expo codebase for every screen — iOS, Android, and web — instead of maintaining a Next.js web app and a React Native mobile app as two separate frontends. Expo Router's file-based routing produces native screens on iOS/Android and a React Native Web build for the browser from the same component tree, so a feature (e.g. Sponsor a Tithi) is built once and ships to all three surfaces instead of twice. EAS Build/Submit already unifies the iOS/Android pipeline; the same pipeline now also produces the web bundle, and `expo-updates` can push copy/content fixes to the app surfaces over the air between store reviews — real value for a volunteer-run nonprofit that cannot wait a week for an App Store review to fix a typo in a festival date. React Native Web has historically lagged a dedicated SSR framework on the SEO-critical parts of the public site (§4.1.3, §5.4: meta tags, structured data, sitemap, fast first paint on elder devices). **Mitigation:** Expo Router's static/server rendering output mode pre-renders the public web routes (Home, Events, Donate, About, Policies) with real per-page HTML and metadata; the Public Web & SEO module is scoped against this rendering mode from the start, not client-only SPA rendering. Live Darshan's Picture-in-Picture, AirPlay, and Google Cast requirement (§4.1.2) still needs a custom Expo dev client, not the vanilla Expo Go app — booked as the Sprint 1 spike (ARCH-2) before any feature work depends on it. | E5: Expo (Router, custom dev client) as the single Web + iOS + Android codebase; EAS Build/Submit for all three targets
A6: Admin utility & content management | B6: Yes | C6: Payload CMS (self-hosted, Postgres adapter) · Previous approach: separate Vite + React SPA built from scratch | D6: User has directed Payload CMS as the admin and content layer, replacing a bespoke admin SPA. Payload generates a production admin UI — sidebar navigation, list views with sort/filter/search/bulk actions, a document editor, and a Cmd+K jump-to search — directly from a collection config, so most of the RFP's 20 admin sections (§3.4) exist as configuration, not hand-built screens. Per-collection and per-field access control covers a large share of the granular-permissions requirement (§4.4.1). Built-in drafts/versioning and document locking cover much of the audit-trail and concurrent-edit requirements (§4.4.1, §4.5.3) without a custom implementation. Content authored in Payload — announcements, pages, FAQ, policies, translation strings — is exposed over a REST/ GraphQL API the Expo app consumes, which is exactly the "admin can edit everything, including the landing page copy" outcome the user wants. Payload runs on Node.js/Next.js with its own Postgres adapter — a second server-side stack alongside the Python FastAPI service, a real increase in operational surface versus one backend. **Mitigation:** both services point at the same Postgres 16 instance (Payload owns content/CMS tables, FastAPI owns transactional business tables — money, membership, dues, RSVPs), so there is one database to operate and back up, not two. Screens the RFP needs that don't map onto a generic Payload collection view (Member 360, the Operations Dashboard, the two-person money-confirmation modal, the dues-aging report) are built as custom Payload admin components, keeping exactly one admin application in production rather than a second bespoke app. Payload has no built-in MFA or no-code role editor — both are named as explicitly custom-built work in the Auth & RBAC module rather than assumed free. | E6: Payload CMS as the admin utility and content layer, self-hosted, Postgres adapter, custom admin views for the screens a generic collection view can't express
A7: Backend framework | B7: Yes | C7: FastAPI + SQLAlchemy + Pydantic (Python) · Previous approach: Django 5 + Django REST Framework | D7: User has directed FastAPI as the single backend framework, replacing the earlier Django/DRF plan. FastAPI generates the OpenAPI 3.1 schema natively from route and Pydantic-model type hints — no separate schema-generation library needed — which keeps the packages/api-client codegen pipeline simple. Native async support fits notification fan-out (APNs/FCM/Web Push/email), concurrent payment-processor webhooks (Stripe + PayPal), and the Phase 3 AI Chat streaming workload on the same stack the rest of the platform already runs, rather than reserving a second, "substantially different" stack for that one workstream as previously planned — RFP §4.3's anticipated stack difference is now just "the same FastAPI service, a different workload." FastAPI doesn't bundle Django's batteries — no built-in ORM, admin site, auth system, or migrations tool. **Mitigation:** SQLAlchemy 2.x is the ORM, Alembic handles migrations, and a small shared base-model mixin (id, created/updated timestamps, actor tracking, soft-delete flag, optimistic-lock version column) plus one audit-log table replace what django-safedelete/django-simple-history gave for free — this is booked as its own story (DB-2) rather than assumed to come with the framework. The admin-site gap is filled entirely by Payload CMS (above), so FastAPI never needs one of its own. Celery (or an RQ-based equivalent) still handles push fan-out, scheduled publish, and dues-reminder dunning as background jobs outside the request cycle. | E7: FastAPI + SQLAlchemy 2.x + Alembic + Pydantic for the core platform API and the Phase 3 AI Chat service — one Python backend throughout
A8: Primary database | B8: No | C8: PostgreSQL 16 · MySQL 8 · migrate/extend JCA's existing database | D8: Relational integrity is non-negotiable for money and membership data. Postgres adds JSONB for flexible content blocks (event schedules, quiz questions), `pg_trgm` + `unaccent` for typo-tolerant, diacritic-aware search over Sanskrit/Prakrit terms (§4.4.1), and row-level audit triggers that back the immutable audit log. Both the FastAPI service and Payload CMS target this same Postgres instance, in separate schemas, so there is one datastore to provision, back up, and monitor. RFP §1.1 states a database is "already available," and §3.4 item 15 says "the database of library books is already available." We do not yet know what that system is. **Mitigation:** a dedicated audit and migration-path story is booked in the Data Migration Planning module before the schema is frozen, so existing data is assessed before Postgres is committed to as the system of record. | E8: PostgreSQL 16, pending the Phase 0 legacy-database audit
A9: Payment processor | B9: No | C9: Stripe + PayPal Commerce · Stripe only · Authorize.net · Donorbox/Givebutter hosted widgets | D9: Stripe covers cards, Apple Pay, Google Pay, ACH, and Stripe Billing for recurring giving with pause/edit/cancel in two interactions or fewer (§2.2). Payment Element (web) and the Stripe React Native SDK keep the platform at PCI SAQ-A — card numbers never touch our servers. The Refunds API is idempotent, which fits the two-person-confirmation rule for money (§4.4.1) cleanly: one admin initiates, the second confirms, then the refund call fires once. Stripe offers a reduced processing rate for registered 501(c)(3) nonprofits. Stripe's own PayPal payment method is not available to US-based Stripe accounts, but §4.1.3 explicitly requires PayPal support — so Stripe alone does not satisfy the RFP. PayPal Commerce Platform is integrated as a second, separate rail specifically for that requirement. **Rejected:** Authorize.net has no clean native-wallet (Apple Pay/Google Pay) story for a React Native app. Donorbox/ Givebutter are rejected because their hosted-widget model can't be embedded natively inside the Expo app's donation flow and would fork receipts and donation records outside our single source of truth (§2.2). Receipts are generated by our own backend, not by the processor — 501(c)(3) receipts must carry JCA's EIN and "no goods or services were provided" language, which is JCA-specific content no processor template provides. Zelle/bank transfer shown in the mockup is treated as off-platform and recorded via the admin's manual donation-entry component, not as a live payment rail. | E9: Stripe (cards, Apple Pay, Google Pay, ACH, Billing) as primary
A10: Search | B10: No | C10: PostgreSQL full-text search + pg_trgm + unaccent · Elasticsearch · Meilisearch (from day one) · Algolia | D10: §4.4.1 requires typo-tolerant search across members, families, donations, events, and posts, including Sanskrit/Prakrit terminology and name transliterations. Postgres FTS with `pg_trgm` (trigram similarity) and `unaccent` (diacritic-insensitive matching) covers this without standing up a second datastore, which keeps Phase 1 infrastructure simpler and the audit surface smaller. Full-text search over scanned/OCR'd PDF scripture and lecture content in the Phase 2 Library & Jinvani module is exactly the workload Postgres FTS starts to strain under — ranking quality and multi-language stemming are weaker than a dedicated search engine. **Mitigation:** Meilisearch is introduced in Phase 2, precisely when that workload appears, rather than paying its operational cost from day one for admin/member search Postgres already handles well. | E10: Postgres FTS + pg_trgm + unaccent in Phase 1; add Meilisearch in Phase 2 for library/lecture full-text search
A11: Cloud hosting | B11: No | C11: GCP (Cloud Run + Cloud SQL + Cloud Storage/CDN) · AWS (ECS/Fargate + RDS + S3/CloudFront) | D11: Google for Nonprofits offers substantial Cloud credit grants to registered 501(c)(3) organizations — directly relevant to JCA's budget as a nonprofit. Cloud Run's scale-to-zero model suits a congregation-sized traffic pattern with sharp peaks around festivals (Paryushan, Diwali, MJK) and otherwise-quiet weekdays, and hosts the FastAPI service and the Payload admin/CMS app as two independent Cloud Run services against the same Cloud SQL instance. Cloud Build gives a native CI/CD path matching the team's existing GCP experience. Cloud Run cold starts add latency on the first request after an idle period — mitigated with a minimum-instance-count of 1 on both the FastAPI service and the Payload admin service so the admin utility and payment endpoints never cold-start. AWS ECS/Fargate + RDS + S3/CloudFront is recorded as the equivalent alternative if JCA's board has an existing AWS relationship or credit commitment; the Terraform/ IaC layer is written to keep this swap feasible without an application-code rewrite. | E11: For example : GCP — Cloud Run (FastAPI + Payload), Cloud SQL (Postgres), Cloud Storage + Cloud CDN, Secret Manager, Cloud Build
A12: Live Darshan streaming | B12: No | C12: Player only, JCA-supplied HLS URLs · Fully managed live encoding (Mux / Cloudflare Stream Live) | D12: RFP §3.4 item 14 scopes the admin's job as configuring stream-source URLs per tradition (HLS URLs, fallback, scheduled on/off windows) and monitoring stream health — not operating an encoder. Building only the player, PiP, AirPlay/Cast, and health-check layer keeps several sprints of encoding infrastructure out of scope that the RFP never asked for. If JCA does not already have a hardware or software encoder producing HLS streams from the five shrines, this decision assumes infrastructure that may not exist. **Mitigation:** this is confirmed with JCA during Phase 0 — if JCA has no encoder, a managed live-encoding service becomes a separately-priced change order, not silent scope creep absorbed into Phase 1. | E12: Player only in Phase 1; managed encoding is a change order if JCA has no encoder
A13: Monorepo tooling | B13: No | C13: Turborepo + pnpm workspaces · Nx · separate repos per surface | D13: RFP §3.1 requires every surface to share the same design tokens (colors, typography, spacing, radii, shadows). A single `packages/tokens` source of truth — generating CSS custom properties for the Payload admin theme and a React Native theme object for the Expo app from the same token file — satisfies that requirement structurally rather than by convention. A generated TypeScript API client from FastAPI's OpenAPI schema in `packages/api-client` eliminates drift between the backend contract and the Expo app's usage of it. EAS Build needs explicit configuration to build an Expo app that lives inside a monorepo rather than at a repo root — this is booked as a named subtask in Project Setup & CI/CD (Sprint 1) rather than discovered mid-Phase-1. Payload's own Next.js app also needs to be told where the monorepo's shared packages live. | E13: Turborepo + pnpm workspaces: apps/expo (Web + iOS + Android), apps/admin (Payload CMS), packages/tokens, packages/ui, packages/api-client; backend in services/api (FastAPI)
A14: Localization approach | B14: No | C14: Centralized LocalizationStrings collection in Payload · Per-surface translation files (i18next per app, duplicated) | D14: RFP §3.1 explicitly requires localization to be centralized — "strings live in the backend or a shared catalog, not duplicated per surface." A `LocalizationStrings` collection in Payload, with English/Hindi/ Gujarati fields per key, gives the admin utility's translator-review workflow (§5.2) a native fit: Payload's draft/publish and versioning already model "submitted, pending review, live" for a string, rather than a separate review workflow built from scratch. A Payload-served catalog adds a network dependency for strings that per-surface i18next files would resolve at build time — mitigated by aggressive client-side caching of the catalog in the Expo app with a version/ETag check, so steady-state usage never re-fetches unchanged strings. | E14: Centralized LocalizationStrings collection in Payload, served via its API, cached in the Expo app with version-checked invalidation

Sheet Phase 0 — Foundation
A1: Phase 0 — Foundation
A2: Designs reviewed and approved, design system locked, skeletons deployed, auth working — gates all feature work per RFP §4.1.1.
A4: ID | B4: Module | C4: User Story | D4: Description
A5: DR-1 | B5: Design Review | C5: Website review — public website screens reviewed and approved so they are final and ready to build. | D5: Every public website screen (homepage, info pages, event browse, donate, newsletter sign-up, sign-in entry points) is presented to the JCA project committee at phone, tablet, and desktop breakpoints. Feedback is incorporated and written sign-off is recorded; approved screens are frozen as the build reference.
A6: DR-2 | C6: App review — iOS and Android app screens reviewed and approved so they are final and ready to build. | D6: All mobile app screens (Home, Live Darshan, Calendar, Donate flows, Community, Profile/More, etc.), including dark-mode and AA-contrast variants, are reviewed with the JCA project committee. Written sign-off is recorded; approved screens are frozen as the build reference.
A7: DR-3 | C7: Web app review — signed-in member web experience reviewed and approved so it is final and ready to build. | D7: The authenticated member web dashboard and navigation (mirroring the mobile information architecture) are reviewed with the JCA project committee at desktop breakpoints. Written sign-off is recorded; approved screens are frozen as the build reference.
A8: DR-4 | C8: Web admin utility review — admin utility screens reviewed and approved so they are final and ready to build. | D8: The Payload admin re-skin, sidebar grouping, Operations Dashboard, Member 360, and other custom admin views are reviewed with the JCA project committee. Written sign-off is recorded; approved screens are frozen as the build reference.
A9: ARCH-1 | B9: Cloud Architecture & Platform Setup | C9: The stack ratified and recorded as ADRs so every subsequent decision traces back to a documented rationale. | D9: ADRs written for the unified UI framework (Expo), the admin/content layer (Payload CMS), the backend framework (FastAPI), database, payments, search, hosting, streaming, and monorepo tooling — matching the Tech Decisions sheet; each ADR includes the offense/defence and a named owner.
A10: ARCH-2 | C10: A spike proving Picture-in-Picture, AirPlay, and Google Cast work in an Expo dev-client build before Live Darshan is scheduled as a feature sprint. | D10: A throwaway Expo dev-client build demonstrates PiP on iOS, AirPlay casting to an Apple TV, and Google Cast to a Chromecast, all playing a test HLS stream; findings documented, blocking risks flagged.
A11: ARCH-3 | C11: The monorepo topology (Turborepo + pnpm) scaffolded so every surface shares tokens and the generated API client from day one. | D11: Monorepo created with apps/expo (Web + iOS + Android), apps/admin (Payload CMS), packages/tokens, packages/ui, packages/api-client, and services/api (FastAPI); a shared token change in packages/tokens visibly propagates to a placeholder screen in the Expo app and a placeholder page in the Payload admin theme.
A12: ARCH-4 | C12: Environment topology (local, staging, production) defined so every surface and both backend services deploy predictably. | D12: Environment matrix documents URLs, config sources, and data-isolation rules for local/staging/production across the Expo app, the Payload admin app, and the FastAPI service; admin utility staging vs production promotion flow (including Payload content promotion) documented per RFP §4.4.2.
A13: DB-1 | C13: The nine-domain data model designed and reviewed so every subsequent feature sprint builds against a stable schema. | D13: ERD covers all nine domains (Identity & Access, Membership, Giving, Sponsorship, Events & Facilities, Community, Content, Education & Seva, Platform Operations) per docs/03-database-schema.md, split between Payload-owned content collections and FastAPI-owned transactional tables; reviewed by JCA's technical advisor per RFP §4.1.1.
A14: DB-2 | C14: The cross-cutting conventions (UUID PKs, soft-delete tombstone, optimistic-locking version column, audit trail) applied to every FastAPI-owned table via a shared SQLAlchemy base model, since FastAPI doesn't bundle these the way Django's ecosystem does. | D14: A shared SQLAlchemy declarative base/mixin provides id, created_at, updated_at, created_by, updated_by, deleted_at, and version on every business table; a companion audit-log table records every state-changing write with actor and before/after values; Alembic migration generates all of it cleanly on a fresh database.
A15: DB-3 | C15: Baseline Alembic migrations and seed data so every developer can stand up an identical local Postgres database for both the FastAPI service and Payload. | D15: Initial FastAPI migration set (Alembic) and Payload's own migration/config apply cleanly on a fresh Postgres 16 instance; seed-data fixtures populate roles, permissions, the five traditions, and a handful of demo members/events for local development.
A16: DB-4 | C16: Pg_trgm and unaccent enabled with indexes on searchable name/content fields so search is typo-tolerant and diacritic-aware from day one. | D16: pg_trgm and unaccent extensions enabled on the Postgres instance; trigram indexes added on member_profile.display_name, event.title, and post.body; a manual test query with a typo and a missing diacritic both return the expected row.
A17: API-1 | C17: FastAPI's native OpenAPI 3.1 schema generation wired up and published so the frontend contract is always in sync with the actual routes, with no separate schema-generation library to maintain. | D17: OpenAPI schema auto-generates at /openapi.json straight from FastAPI route and Pydantic-model type hints; a Swagger/Redoc UI is reachable in the staging environment; schema includes example payloads for at least the auth and member-profile endpoints.
A18: API-2 | C18: A API client generated from the FastAPI OpenAPI schema, plus a typed client for Payload's REST/GraphQL content API, into packages/api-client, so the Expo app calls both backends through one typed interface. | D18: A codegen script produces a typed client from FastAPI's live schema and a typed client from Payload's generated types; a change to a FastAPI Pydantic model or a Payload collection field is reflected in the generated client on the next codegen run without manual edits; both clients are published as one workspace package consumed by the Expo app.
A19: API-3 | C19: An API versioning and deprecation policy documented so breaking changes never surprise a shipped mobile client, per RFP §3.1. | D19: Versioning policy documented (URL-prefixed /api/v1/); deprecation window defined (minimum 90 days with a Sunset header); policy referenced in every ADR touching the API surface.
A20: API-4 | C20: A standard error envelope and pagination/filtering convention so every FastAPI endpoint behaves predictably across all surfaces. | D20: Error responses follow a consistent {code, message, field_errors} shape; list endpoints support cursor-based pagination and a common filter/sort query-param convention; documented in the API contract.
A21: SETUP-1 | C21: Three project skeletons — the FastAPI backend, the Payload admin/CMS app, and the single Expo app — created with CI so every surface builds and lints on every push, per RFP §4.1.1. | D21: Each of the three skeletons has a passing CI pipeline running build + lint + test on every push; badge visible in each app's README; a trivial change to each surface triggers and passes its pipeline.
... A25: SETUP-5 | C25: Cloud Build (or equivalent) wired to deploy on merge to main so every accepted change reaches staging without a manual step. | D25: A merge to main triggers build, test, and deploy to staging for the affected surface(s) only (FastAPI, Payload, or the Expo app); a failed pipeline blocks the deploy and notifies the team.
A26: MIG-1 | B26: Data Migration Planning | C26: The existing database(s) referenced in the RFP audited so we know what, if anything, must be migrated before the new schema is frozen. | D26: Audit report documents the existing system(s), including the library-book database from RFP §3.4 item 15, its schema, row counts, and export capability; migration-path recommendation delivered.
A27: MIG-2 | C27: A field-by-field data-mapping sign-off so we agree, in writing, which legacy fields map to the new schema and which are intentionally dropped, before any data moves. | D27: A mapping document lists every legacy field (member records, library catalog, any donation history found) against its destination in the new schema or an explicit 'not migrated' decision with a stated reason; JCA project committee signs off before the migration script is written.
A28: MIG-3 | C28: A rehearsed one-time ETL script with a dry run and a rollback plan so cutover from legacy data happens on a known-good schedule, not a live scramble. | D28: ETL script runs successfully against a copy of the legacy data into a staging database; a dry-run report shows row counts in vs. out per table with any rejected/unmapped rows flagged; a documented rollback plan restores the pre-migration state if the cutover run fails partway.
A29: PAYSETUP-1 | B29: Payment Provider Setup | C29: A Stripe account created and verified under JCA's 501(c)(3) EIN so nonprofit processing rates and payout banking are confirmed before any payment feature is built. | D29: Stripe account is created under JCA's legal entity, EIN, and bank account; nonprofit discounted-rate status is applied and confirmed; account is fully verified (no outstanding Stripe requirements) before the Payments & Billing sprint begins.
A30: PAYSETUP-2 | C30: A PayPal Commerce Platform business account set up as the secondary payment rail so members who prefer PayPal are covered per the RFP requirement. | D30: PayPal Commerce Platform business account created under JCA's legal entity; account verified and linked to JCA's bank account; live API credentials available for integration.
A31: PAYSETUP-3 | C31: Sandbox/test-mode API keys for both Stripe and PayPal provisioned into the credentials vault early so payment feature sprints aren't blocked waiting on account approval. | D31: Stripe and PayPal sandbox/test-mode keys are stored in Secret Manager and referenced from the credentials vault before the Payments & Billing sprint starts; a test charge and a test PayPal payment both succeed against sandbox from a throwaway script.
A32: PAYSETUP-4 | C32: Webhook endpoints and payout bank details test-verified for both processors so real donations settle into JCA's bank account correctly from day one. | D32: Stripe and PayPal webhook endpoints are registered and receive a successful test event from each processor's dashboard; a test payout completes to JCA's actual bank account in sandbox/test mode where the processor supports it, confirming account and routing details are correct.
A33: STORE0-1 | B33: App Delivery Platform Enrollment | C33: JCA enrolled in the Apple Developer Program as an organization account so we can distribute test builds via TestFlight and, later, submit to the App Store. | D33: Apple Developer Program organization enrollment completed under JCA's legal entity (D-U-N-S number verified); JCA is the account holder of record; vendor engineers are added as team members with the appropriate roles in App Store Connect.
A34: STORE0-2 | C34: JCA enrolled in the Google Play Console as an organization developer account so we can use Play's testing tracks and, later, publish to the Play Store. | D34: Google Play Console organization account created and verified under JCA's legal entity; the one-time developer registration fee is paid from JCA's account; vendor engineers are added with scoped Play Console access.
A35: STORE0-3 | C35: TestFlight internal testing enabled from Sprint 1 so every EAS build reaches the JCA committee's iPhones automatically, with no Apple review required. | D35: TestFlight internal testing group created in App Store Connect (up to 100 App Store Connect users, no Apple review needed); the JCA committee's Apple IDs are added as internal testers; a build distributed via EAS Submit appears on their devices without a manual upload step. External testing (public link, up to 10,000 testers, requires a lightweight Beta App Review) is documented as the path for the wider pre-launch beta in Store & Launch Readiness.
A36: STORE0-4 | C36: A Google Play Internal Testing track enabled from Sprint 1, with a Closed Testing track planned ahead of time, so Android builds reach testers immediately and we satisfy Google's mandatory pre-production testing requirement without a last-minute scramble. | D36: Play Console Internal Testing track live (up to 100 testers, available within minutes, no review) with the JCA committee added as testers; a build distributed via EAS Submit appears on the Internal Testing track without a manual upload step; the Closed Testing track is scoped and scheduled to open with at least 12 opted-in testers running for a continuous 14-day period, since new Play Console accounts must complete this before applying for full production access.
A37: STORE0-5 | C37: The EAS Build/Submit pipeline wired directly to TestFlight internal testing and the Play Internal Testing track so every merged build reaches testers without a manual upload step. | D37: A merge to the release branch triggers an EAS build and an automatic EAS Submit to both TestFlight internal testing and the Play Internal Testing track; the JCA committee receives both builds without any manual App Store Connect or Play Console interaction.
A38: AUTH-1 | B38: Auth, Identity & RBAC | C38: Sign in with Apple, Google, or email/password on any surface so members have one identity everywhere, per RFP §3.1. | D38: All three sign-in methods work on iOS, Android, and Web from the single Expo app; signing in on one surface and then opening another surface recognizes the same account; the FastAPI backend issues and validates the session/JWT tokens for all three providers.
A39: AUTH-2 | C39: Registration to capture member-ID linkage, family-record initiation, and gotra so the account starts connected to the family and tradition. | D39: Registration flow collects member ID (or issues one), initiates a family record with the registrant as primary, and captures gotra and tradition; all three fields visible on the resulting Profile screen.
A40: AUTH-3 | C40: An SSO option for admin sign-in so JCA can use its provider of choice for staff authentication, per RFP §3.1. | D40: SAML or OIDC SSO configurable from a Payload admin settings screen, implemented as a custom Payload authentication strategy (Payload does not ship SSO out of the box); an admin can sign in via the configured SSO provider in addition to Payload's built-in email/password.
A41: AUTH-4 | C41: MFA mandatory at first login so the admin utility meets the security posture since Payload does not enforce MFA by default. | D41: A custom Payload authentication hook blocks completion of first login until an admin enrolls an MFA factor (TOTP at minimum); MFA is enforced on every subsequent login; no bypass path exists for any admin role including Super-Admin.
A42: AUTH-5 | C42: The option to enable MFA on their account so members can add security if they choose, without it being forced. | D42: MFA enrollment is available in Profile > Settings for member accounts; enabling it does not disrupt Sign in with Apple/Google flows; disabling requires re-authentication.
A43: AUTH-6 | C43: Define roles and per-section permission overrides without an engineer redeploying code, so access matches RFP §3.1's minimum seven-role set plus any additional roles we need. | D43: A Roles collection in Payload, read by a generic access-control layer at runtime, lets a Super-Admin create/edit roles and assign per-section read/write/approve/money permissions — Payload's default access functions are static code, so this dynamic layer is the custom-built piece on top of them; a 'what can this role see and do' preview is available; the Treasurer/Pathshala-coordinator/Communications-chair scenarios from RFP §4.4.1 are each configurable without code changes; member-facing roles (Family Primary, Pathshala Parent, Committee Member) are modeled the same way inside the FastAPI service for app-side permissions.
A44: AUTH-7 | C44: Tokens stored in the platform keychain/keystore/HttpOnly cookie so credentials never sit in insecure storage, per RFP §5.1. | D44: The Expo app on iOS stores tokens in Keychain with the strictest applicable accessibility class; on Android it uses Keystore-backed EncryptedSharedPreferences; the Expo app's web build uses HttpOnly, Secure, SameSite=Lax cookies with CSRF tokens on state-changing requests.
A45: AUTH-8 | C45: A first-launch Splash/Welcome screen establishing Jain identity before any utility, so the first impression of the app is reverent, not transactional, per RFP §4.1.2 and the walkthrough's slide 4. | D45: Splash shows the JCA logo on an ivory medallion, the Navkar Mantra in a serif face, the ratnatraya ornament, and the five-shrine context (Mahavir, Adinath, Upashray, Shrimad, Dadawadi), with a single Get Started CTA; shown automatically on first open and never again unless the user signs out; the web build of the same Expo app serves the public homepage with a Sign In CTA as its equivalent entry point (no separate splash screen on web).

Sheet Phase 1 — v1.0
A1: Phase 1 — v1.0 (initial launch)
A2: Every P1 feature live on iOS, Android, Web, and Admin. App Store + Play Store approved. Public web launched. RFP §4.1.
A4: ID | B4: Module | C4: User Story | D4: Description
A5: HP-1 | B5: Home & Panchang | C5: An eight-section Home dashboard so members have a single daily-touch landing page with everything they check each morning. | D5: Home renders greeting, Panchang card, Today's Sponsor, Thought of the Day, Daily Quiz, Quick Actions, Center Hours, and Upcoming Events + Feed preview, matching the walkthrough's slide 3; pull-to-refresh updates Panchang and feed.
A6: HP-2 | C6: The daily Jain Panchang (tithi, parva indicator, sunrise, sunset, pratikraman time) cached locally so members can check it even without a connection. | D6: Panchang card shows all five data points; mobile caches the last-fetched Panchang for offline display; web shows the same data without requiring sign-in per RFP §4.1.2.
A7: HP-3 | C7: Configure the Panchang data source and set manual overrides so incorrect calculated data can be corrected without a deploy. | D7: Admin Religious Calendar section exposes a Panchang data-source configuration and a manual-override field per date; overrides take effect immediately on all surfaces.
A8: HP-4 | C8: A Daily Quiz with a streak counter so members have a reason to open the app every day. | D8: One quiz question served per day; answering correctly/incorrectly is recorded once per user per day; a visible streak counter increments on consecutive correct days and resets on a missed day.
A9: HP-5 | C9: Author Thought of the Day content and manage the quiz question bank so Home stays fresh without engineering involvement. | D9: Content section lets an admin schedule a Thought of the Day per date and add/edit/retire quiz questions with a correct-answer flag; scheduled publish works for both content types.
A10: HP-6 | C10: Quick Actions and Center Hours with an Open-Now indicator so members can act on the most common tasks and know if the center is open right now. | D10: Quick Actions link to Darshan, Donate, Calendar, Gallery, and Volunteer; Center Hours shows today's hours with a live Open/Closed indicator based on the current time.
A11: CAL-1 | B11: Calendar & Events | C11: A month-grid calendar with festivals, parva days, and JCA events marked so members can see everything happening at a glance. | D11: Month grid shows saffron-replaced (brand-compliant) markers for festival/parva days and separate markers for JCA event days per the walkthrough's slide 8; today is highlighted; tapping a day shows that date's events; swipe changes month.
A12: CAL-2 | C12: An event detail view with full schedule, location, RSVP, and calendar export so members can commit to attending and add it to their phone. | D12: Event detail shows hero image, full multi-block schedule, shrine/location with map preview, RSVP button with live attendee count, sponsor-this-event link, and an add-to-calendar action per the walkthrough's slide 22.
A13: CAL-3 | C13: RSVP to an event and see a waitlist state if it's full so members know where they stand. | D13: RSVP button shows Confirmed/Waitlisted/Full based on the RSVP cap; a waitlisted member is promoted automatically if a confirmed spot opens; cancellation frees the spot immediately.
A14: CAL-4 | C14: Full event lifecycle management (create, edit, publish, retire) with categories, RSVP cap, and sponsorship tiers so admins run every event through one tool. | D14: Event editor supports hero media, multi-block schedule, location, category (Religious/Cultural/Educational), RSVP cap, waitlist, sponsorship tiers, and linking a donation cause; publish/retire states are explicit and reversible within the soft-delete window.
A15: CAL-5 | C15: A calendar conflict view across events, pooja, abhishek, and facility bookings so double-bookings are caught before publish. | D15: Conflict view overlays events, religious-calendar slots, and facility bookings on one calendar; a scheduling conflict is visually flagged before an admin can publish the conflicting item.
A16: CAL-6 | C16: Event category management (Religious/Cultural/Educational) so Cultural & Religious events surface correctly as filterable categories per RFP §4.1.2. | D16: Category CRUD available in admin; member-facing Calendar supports filtering by category; Cultural events (Garba, plays, music programs) correctly tag as Cultural.
A17: CN-1 | B17: Content & Newsletter | C17: Author and schedule announcements that push to all members and pin in the feed so time-sensitive news reaches everyone. | D17: Announcement editor supports send-now or schedule-for-later; on publish, a push notification fans out and the announcement auto-pins in the Community Feed; preview renders as it will appear on iOS, Android, and web before publish, per RFP §4.4.1.
A18: CN-2 | C18: About Us, Contact, and Help pages so members can learn JCA's history and get in touch. | D18: About Us shows JCA history content; Contact shows address, phone, email, directions, hours, and social links; Help combines FAQ with a contact form that routes submissions to admin.
A19: CN-3 | C19: Manage the FAQ taxonomy and route contact-form submissions so Help content stays organized and no inquiry is lost. | D19: FAQ entries are categorized and orderable; contact-form submissions appear in an admin queue with status tracking (new/responded/closed).
A20: CN-4 | C20: A public Board of Trustees and Executive Committee directory so members know who governs JCA. | D20: Directory shows name, role, term, opt-in photo, and bio for each member; photo display respects each individual's opt-in flag.
A21: CN-5 | C21: A newsletter archive with the current issue and back issues so members can catch up on anything they missed. | D21: Current issue displayed prominently; archive lists back issues chronologically; share and save actions work on mobile and web.
A22: CN-6 | C22: Subscribe to JCA's mailing list from the public web so members can stay informed without creating a full account. | D22: Public opt-in form captures email with double opt-in confirmation; subscription integrates with JCA's existing email-marketing tool; admin can view and export the subscriber list.
A23: PAY-1 | B23: Payments & Billing Infrastructure | C23: Stripe integrated with Apple Pay, Google Pay, card, and ACH so every donation/dues/sponsorship flow has a working payment rail. | D23: Stripe Payment Element live on web; Stripe React Native SDK live on iOS/Android with native Apple Pay and Google Pay sheets; a test charge completes end-to-end and a payment_transaction row is written.
A24: PAY-2 | C24: PayPal Commerce Platform integrated as a second payment rail so the RFP's explicit PayPal requirement is satisfied alongside Stripe. | D24: PayPal button/flow available on all donation, dues, and sponsorship checkout screens as an alternative to Stripe; a completed PayPal payment writes the same payment_transaction shape as a Stripe payment.
A25: PAY-3 | C25: An explicit confirmation screen with itemized lines before any charge so members always know exactly what they're paying for, per RFP §2.2. | D25: Every payment flow (donation, dues, sponsorship, subscription, facility deposit) routes through a shared confirmation screen with itemized amount, cause/purpose, and payment method before the charge fires; no charge occurs without this screen.
A26: PAY-4 | C26: Every payment operation to be idempotent so a network retry or double-tap never double-charges a member. | D26: Every charge request carries a client-generated idempotency key; a repeated request with the same key returns the original result without creating a second transaction; verified with an automated retry test.
A27: PAY-5 | C27: A downloadable PDF tax receipt for every donation and a consolidated year-end statement so 501(c)(3) giving is documented, per RFP §2.2. | D27: Every completed donation generates a PDF receipt with JCA's EIN and 'no goods or services' language within seconds of payment; a year-end statement PDF aggregates all giving for a tax year and is downloadable on demand.
A28: PAY-6 | C28: Record off-platform donations (cash, check, in-kind) and issue refunds, both gated by the two-person rule, so financial operations stay auditable. | D28: Manual donation-entry form generates a receipt identically to an on-platform donation; a refund action requires a second admin's confirmation with their own credentials before it commits; both actions write audit-log entries naming both actors.
A29: ADM-1 | B29: Admin — Shell, Dashboards & Members | C29: All 20 RFP admin sections modeled as Payload collections/globals with sensible sidebar grouping, so admins get a predictable navigation shell without a bespoke admin app built from scratch, per RFP §3.4. | D29: All 20 admin sections exist as Payload collections or globals, grouped in Payload's built-in sidebar in the RFP's specified order (stubs where a section's feature isn't built yet); active section is visually indicated using the re-themed Payload admin from DES-10; no custom shell/routing code is written since Payload generates this from the collection config.
A30: ADM-2 | C30: Payload's built-in search extended to jump straight to a member's Member 360 profile, so admins can find anything without hunting through the sidebar, per RFP §4.4.1. | D30: Payload's built-in global search/jump-to indexes members by name and links a result directly to the custom Member 360 view (ADM-4), not just the raw Members collection row; keyboard-only operation works end-to-end; no separate command-palette component is built since Payload ships one.
A31: ADM-3 | C31: A custom Operations Dashboard home page showing moderation queue depth, donation totals, upcoming events, dues-aging alerts, member growth, and recent audit entries, per RFP §4.5.4. | D31: Dashboard renders all six specified widgets with live data, built as a custom Payload admin view (this aggregate cross-collection view is not something a generic Payload collection screen can express); each widget links through to its full section; loads in under 2 seconds on staging with representative seed data.
A32: ADM-4 | C32: A Member 360 view so a member's contact info, family, membership, donations, dues, volunteer hours, Pathshala enrollment, RSVPs, posts, and sign-in audit are all one click away, per RFP §4.5.1. | D32: Member 360 is a tabbed single profile page, built as a custom Payload admin view that aggregates data from both Payload collections and the FastAPI service, covering all nine listed data categories; every tab loads without navigating away from the profile; used as the destination for Members & Families, Support, and Moderation sections.
A33: ADM-5 | C33: Bulk-import members via CSV so onboarding JCA's existing congregation doesn't require one-by-one entry, per RFP §4.4.1. | D33: A custom Payload admin action (Payload has no built-in generic CSV import) validates required columns, previews a diff before commit, reports per-row errors without failing the whole batch, and writes one audit-log entry summarizing the import.
A34: ADM-6 | C34: Rely on Payload's built-in document locking and versioning so two admins editing the same record never silently overwrite each other, per RFP §4.4.1. | D34: Payload's built-in document-locking shows 'X is already editing this document' when a second admin opens a record concurrently, and its versioning prevents a stale save from silently overwriting changes — verified against the RFP's concurrent-edit requirement rather than built from scratch; any gap found (e.g. a moderation-queue-specific presence indicator Payload's per-document lock doesn't cover) is scoped as a small custom addition, not a full presence system.
A35: ADM-7 | C35: Resolve sign-in support tickets and trigger a password reset for a member so admins can help someone locked out without engineering involvement. | D35: From the Member 360 view, an admin can view a member's sign-in audit trail and trigger a password-reset email or unlock an account via a custom action that calls the FastAPI auth service; an audit-log entry is recorded for the action.
A36: DON-1 | B36: Donations & Causes | C36: A Causes list with progress bars and quick-give amount chips so giving takes one tap, per the walkthrough's slide 10. | D36: Causes list shows active causes with progress bar, raised-vs-goal, quick-give chips ($51/$108/$251/$501/$1008/custom), a recurring toggle, and the 501(c)(3) badge; donation is available to unauthenticated visitors on web per RFP §3.4.
A37: DON-2 | C37: An anonymous toggle and memorial/honoree text field on any donation so members can give privately or in someone's memory, per RFP §2.2 privacy-by-default. | D37: Anonymous toggle hides the donor's name from any public recognition surface (Sponsors of the Month, feed); memorial/honoree free-text field appears on the donation form and prints on the receipt when filled.
A38: DON-3 | C38: Causes tied to upcoming events to automatically rise to the top of the list with a countdown, so event-based giving is prioritized, per RFP §4.1.2. | D38: A cause linked to an event shows a countdown to the event date and an event-tied goal-progress bar; linked causes sort above unlinked causes as the event date approaches, per a configurable prioritization window.
A39: DON-4 | C39: Jeev Daya as a permanent, always-visible cause dedicated to animal welfare, per RFP §4.1.2. | D39: Jeev Daya appears in the Causes list at all times regardless of event proximity; admin can link partner-organization information to the cause.
A40: DON-5 | C40: Complete donation history with per-donation receipts and a year-end statement, grouped by year, per the walkthrough's slide 15. | D40: History screen shows a YTD total hero card, year-end statement download, year-pill tabs (current/previous/all years), and monthly grouping with a per-row receipt download.
A41: DON-6 | C41: Create, edit, prioritize, and retire causes, and tie causes to events, so the giving catalog stays current. | D41: Cause CRUD supports goal amount, description, event linkage, and manual priority override; retiring a cause removes it from member-facing lists while preserving its donation history.
A42: SUB-1 | B42: Recurring Giving & Subscriptions | C42: Templated recurring-giving plans (Daily Aarti $11, Bhojanshala $108/mo, Paryushan $2,508/yr) so members can set up giving on autopilot in one tap, per the walkthrough's slide 16. | D42: Set Up New tab shows the three templates plus a custom-amount/frequency option; selecting a template pre-fills amount and frequency and routes to the payment confirmation screen.
A43: SUB-2 | C43: Pause, edit the amount, or cancel any recurring subscription in two interactions or fewer, per RFP §2.2's financial-caution principle. | D43: My Subscriptions tab lists active plans with next-charge date and lifetime total; Pause and Edit-Amount actions are one tap plus one confirmation; Cancel is the same two-interaction limit; no silent auto-renewal changes occur.
A44: SUB-3 | C44: A one-time gift to offer a 'Make monthly' upgrade path so converting to recurring giving doesn't require starting over. | D44: The Thank You confirmation screen after a one-time gift offers a 'Make monthly' CTA that pre-fills a new recurring subscription with the same amount and cause.
A45: SUB-4 | C45: Failed-charge recovery (dunning) for recurring subscriptions so a declined card doesn't silently lapse a member's giving. | D45: A failed recurring charge triggers a retry schedule and a notification to the member with a link to update their payment method; after a configurable number of failures the subscription is paused, not silently cancelled.
A46: SUB-5 | C46: View, pause, edit, or cancel any member's recurring subscription on the member's behalf, gated by the two-person rule for cancel. | D46: Subscription Manager component (RFP §4.5.1) is available from Donations & Causes and from Member 360; cancel-on-behalf requires second-admin confirmation; pause and edit-amount do not.
A47: MFD-1 | B47: Membership, Family & Dues | C47: A family-member list with relationship, DOB, and gotra so the whole family's record lives in one place, per the walkthrough's slide 24. | D47: Family cards show Self, Spouse, Children (with Pathshala badge where enrolled), and Parents, each with avatar, relationship, DOB, and gotra/anniversary; + Add Family Member creates a new family_member record.
A48: MFD-2 | C48: A Pending Dues card with itemized lines and a Pay All Now button, always shown when money is owed, per RFP §4.1.2. | D48: Pending Dues card appears on Home and Family whenever the family's total due is greater than zero, itemizing membership, MJK pass, and Pathshala fee lines; Pay All Now routes through the shared payment-confirmation screen for the full itemized total.
A49: MFD-3 | C49: Membership tier, since-date, and renewal date with a renewal payment flow so members never lapse without knowing. | D49: Profile shows tier, since-date, and renewal date; a Manage button opens the renewal payment flow when renewal is due or upcoming; lifetime-tier members see a distinct, non-renewing state.
A50: MFD-4 | C50: A family record manager to add, remove, and merge family records with family-level vs. member-level dues toggles, per RFP §4.5.1. | D50: Admin can create, edit, merge, and remove family records; a per-family toggle controls whether dues are calculated at the family level or per individual member; merge preserves both families' donation and dues history.
A51: MFD-5 | C51: A dues ledger with running balance and an aging report (30/60/90 days) so overdue dues are visible and actionable, per RFP §4.5.1. | D51: Dues Ledger component shows every issued/paid/comped/waived/refunded entry per family with a running balance; aging report buckets overdue families into 30/60/90-day tiers; a dunning workflow sends templated reminders per bucket.
A52: MFD-6 | C52: Issue dues credits or comps with an audit trail, gated by the two-person rule for money, per RFP §2.2. | D52: Credit/comp issuance requires a reason and a second admin's confirmation before it commits; both actors are recorded in the immutable audit log; the family's ledger reflects the credit immediately after confirmation.
A53: SPN-1 | B53: Sponsorships & Religious Calendar | C53: A Sponsor a Tithi flow with a calendar picker, tiered amounts, and anonymous/memorial options, per the walkthrough's design intent. | D53: Calendar picker shows open vs. booked tithi dates; tiered sponsorship amounts selectable; anonymous toggle and memorial/honoree text available; completed sponsorship writes a sponsorship record linked to the donation.
A54: SPN-2 | C54: Daily Pooja & Abhishek schedules across all five traditions with sponsor recognition, so no tradition is deprioritized, per RFP §2.2's five-traditions-one-sangha principle. | D54: Schedule displays day-by-day pooja/abhishek slots for all five traditions with equal visual prominence; sponsored slots show sponsor recognition (respecting anonymity); sign-in is not required to view, per RFP §4.1.2.
A55: SPN-3 | C55: A specialized Bhojanshala sponsorship flow with a date picker, three meal-type tiers, and a live meal-count, per the walkthrough's slide 11. | D55: Date picker shows open (available) vs. dimmed (booked) dates; tiers are full lunch/sweet box/snack seva with the RFP's example pricing; anonymous toggle and memorial text available; live count of meals served this month displays on the screen.
A56: SPN-4 | C56: A Sponsors of the Month view honoring every donor for the current month, with per-sponsor detail and memorial text, per the walkthrough's slide 14. | D56: Pill tabs filter All/Bhojanshala/Festivals; month total raised and sponsor count shown; per-sponsor row shows name (respecting anonymity), what they sponsored, amount, and date; tapping a sponsor opens their public profile.
A57: SPN-5 | C57: A pooja/abhishek schedule editor and a Bhojanshala kitchen calendar so admins can assign sponsors, mark slots open/sponsored, and track meal counts across the five traditions, per RFP §4.5.2. | D57: Schedule editor supports a daily slot grid across all five traditions with sponsor assignment; kitchen calendar supports meal-type tier configuration and meal-count tracking; both generate sponsor-recognition feeds for Home and Community.
A58: SPN-6 | C58: Configure Sponsor a Tithi tiers and open dates, and approve memorial text, so sponsorship offerings stay curated and appropriate. | D58: Admin can configure tier amounts and open/close individual tithi dates; memorial/honoree text submitted by a member enters a review queue before it displays publicly.
A59: COM-1 | B59: Community Feed & Moderation | C59: An explicit whitelist disclosure, and a member's own pending post never appearing publicly, so members understand and trust the moderation model, per RFP §2.2. | D59: Feed shows a persistent disclosure that member posts are reviewed before appearing publicly; a submitted post shows a 'pending review' state visible only to its author; no optimistic UI ever displays a pending post to any other user, even momentarily.
A60: COM-2 | C60: Compose a post and see pinned admin announcements alongside approved member posts, filterable by All/Admin/Members/Youth, per the walkthrough's slide 17. | D60: Compose stub accepts text and media; feed renders pinned admin posts first, then approved member posts chronologically; pill-tab filters work; reactions are available on both post types.
A61: COM-3 | C61: Report a post so inappropriate content reaches moderation quickly. | D61: Report action available on every post with a reason selector; a report creates a content_report entry visible in the admin moderation queue with the post automatically flagged.
A62: COM-4 | C62: A moderation queue to approve, decline, edit, or flag member posts with real-time presence indicators, per RFP §2.2 and §4.4.1. | D62: Moderation queue lists pending posts with one-click approve/decline/edit/flag actions; a decline requires a reason returned to the author; presence indicator shows when another admin is already reviewing a given post.
A63: COM-5 | C63: Pin/unpin admin posts and manage badges (Youth, Pathshala) so the feed's structure and member recognition stay curated. | D63: Pin/unpin toggle available on any admin-authored post; badge assignment available per member, visible next to their name on posts and profiles.
A64: COM-6 | C64: A reported-content handling workflow so member-flagged posts are triaged distinctly from routine new-post moderation. | D64: Reported posts appear in a distinct queue view with the reporter's reason visible; resolving a report records the outcome and clears it from the queue.
A65: NOT-1 | B65: Notifications & Messaging | C65: Notifications to fan out from the backend to APNs, FCM, Web Push, and email so every member is reachable regardless of surface or preference, per RFP §3.1. | D65: A single notification-send call fans out to all registered device tokens/channels for the target audience; email fallback fires automatically for users who have declined push; delivery status recorded per channel.
A66: NOT-2 | C66: Device registration and per-category notification preferences so members control what reaches them and how, including opt-in birthday/anniversary alerts, per RFP §2.2. | D66: Device token registered on app install/sign-in; Profile > Notifications lets a member toggle categories (events, donations, community, Pathshala) per channel; birthday/anniversary notifications are opt-in per family member, off by default.
A67: NOT-3 | C67: A notification composer with multi-surface preview so admins can see exactly how a push will look before sending, per RFP §4.5.7. | D67: Composer shows a live preview for iOS lock screen, Android notification shade, web push, and email fallback; a deliverability estimate is shown before send; send-now and schedule-for-later both work.
A68: NOT-4 | C68: A segment builder so admins can target a notification by any combination of saved filters, per RFP §4.5.7. | D68: Segment builder combines filters (tab activity, tradition, family role, Pathshala enrollment, membership tier); estimated reach updates live as filters change; segments are saveable and reusable across Notifications and Newsletter.
A69: NOT-5 | C69: A per-notification delivery report with per-surface breakdown so admins know whether a message actually reached people, per RFP §4.5.7. | D69: Delivery report shows sent/delivered/opened (where measurable)/action-taken/bounced/opted-out, broken down by iOS/Android/web/email.
A70: NOT-6 | C70: A transactional template library for receipts, dues reminders, RSVP confirmations, and sign-in alerts, with an audit trail, per RFP §4.5.7. | D70: Templates are editable per notification type with variable placeholders; every edit is recorded in the audit trail; templates are used by the actual sending code paths, not duplicated inline.
A71: PS-1 | B71: Pathshala | C71: A children's class hub showing enrolled children with class badges, today's lesson, and term-fee status, per the walkthrough's slide 18. | D71: Pathshala hub lists each enrolled child with class badge, today's lesson and materials download, term schedule, term-fee status, teacher contact, and attendance streak.
A72: PS-2 | C72: A teacher-contact and parent-feedback flow so members can reach their child's teacher directly. | D72: Teacher contact info is visible per class; a feedback form routes to the assigned teacher's admin queue.
A73: PS-3 | C73: Enrollment management, class roster, and term-fee status tracking so admins run the program without spreadsheets, per RFP §3.4. | D73: Admin can enroll/withdraw a child, view the class roster, and see term-fee status per enrollment; a Pathshala coordinator role can do this without access to refunds, per RFP §4.4.1's granular-permissions example.
A74: PS-4 | C74: Lesson and material publishing plus teacher account assignment so class content flows through the same authoring tools as everything else. | D74: Admin can publish a lesson with attached materials to a class; teacher accounts are assignable to classes with scoped access to only their own roster and lessons.
A75: VOL-1 | B75: Volunteers & Seva | C75: Browse open volunteer opportunities and sign up, plus lifetime seva-hour total, per the walkthrough's slide 19. | D75: Opportunity cards show name, commitment, when, and category (Bhojanshala, Pathshala, Festival, Setup/Cleanup); sign-up is one tap; lifetime seva-hour total is displayed read-only.
A76: VOL-2 | C76: A group-volunteering sign-up option so friends can commit to an opportunity together. | D76: Group sign-up lets a Youth member add multiple names to one opportunity in a single submission.
A77: VOL-3 | C77: Create volunteer opportunities, manage sign-ups, and log hours (admin-entered in v1.0), per RFP §3.4 item 10. | D77: Admin can create/edit/retire opportunities and view sign-ups; admin-entered hour logging updates a member's lifetime total immediately; member-entered hour logging is explicitly deferred to Phase 2 consideration.
A78: VOL-4 | C78: A volunteer-recognition export for Service Awards so seva contributions feed into the Phase 2 recognition program. | D78: Export produces a CSV of lifetime seva hours per member, filterable by date range, suitable as input to the Phase 2 Service Awards selection process.
A79: LD-1 | B79: Live Darshan | C79: Live video from each of the five Jain traditions with a dark-mode UI so members can join darshan remotely, per the walkthrough's slide 7 (Astapadji explicitly excluded). | D79: Five shrine streams selectable (Mahavir, Adinath, Upashray, Shrimad, Dadawadi); live indicator with viewer count; dark-mode UI throughout; Astapadji is not present as a stream option.
A80: LD-2 | C80: Picture-in-Picture and AirPlay/Cast so members can keep watching darshan while using their phone or cast it to a TV, per RFP §4.1.2. | D80: PiP works on iOS and Android; AirPlay works on iOS to an Apple TV; Google Cast works on Android to a Chromecast; all three build on the ARCH-2 spike's proven configuration.
A81: LD-3 | C81: HLS playback with a low-latency option so members can watch darshan from a browser without an app install, per RFP §4.1.2. | D81: Web player supports standard HLS playback and a low-latency mode toggle; playback works on the major desktop and mobile browsers without a plugin.
A82: LD-4 | C82: Configure the HLS stream URL, fallback, and on/off scheduling per tradition, and monitor stream health, per RFP §3.4 item 14. | D82: Admin can set primary and fallback HLS URLs per tradition, schedule on/off windows, and see a stream-health status indicator (up/down/degraded) with recent uptime history.
A83: LD-5 | C83: A notification 15 minutes before evening aarti so members don't miss it, per the walkthrough's slide 4. | D83: A scheduled notification fires 15 minutes before each tradition's configured evening aarti time, respecting the member's notification preferences; tapping it deep-links directly into that tradition's Live Darshan stream.
A84: GOV-1 | B84: Admin — Governance & Operations | C84: An immutable, filterable audit log retained for seven years so every state-changing operation is reviewable, per RFP §4.4.1 and §4.5.3. | D84: Audit log viewer filters by actor, action type, target record, and time range; entries cannot be edited or deleted through any application code path; export available for board/audit-committee review.
A85: GOV-2 | C85: A reusable two-person confirmation modal for every money-moving operation so the two-person rule is enforced consistently everywhere, per RFP §4.4.1. | D85: One shared component handles refunds, dues comps, manual donation entry, and subscription cancel-on-behalf; the initiating admin's request is visible to a second admin who must authenticate to confirm; both signatures are captured in the audit log.
A86: GOV-3 | C86: A soft-delete trash so any deleted record is recoverable for 30 days before a scheduled hard-delete, per RFP §4.4.1. | D86: Every deletable record type appears in a searchable trash view within its section; Restore returns it to its prior state; after 30 days an automated job hard-deletes tombstoned records, with legal-retention exceptions for donation records.
A87: GOV-4 | C87: A feature-flag console for staged rollout (staff, committee, percentage, full) so new features ship safely post-launch, per RFP §4.4.2. | D87: Feature flags can be toggled through the four rollout stages; each flag change is audit-logged; a flagged feature is visible only to the intended population at each stage.
A88: GOV-5 | C88: A maintenance-mode toggle with a configurable banner and ETA so planned downtime is communicated clearly, per RFP §4.4.2. | D88: Toggling maintenance mode displays a banner with a custom message and ETA across all member-facing surfaces; toggle is Super-Admin only and audit-logged.
A89: GOV-6 | C89: An encrypted integration-credentials vault so payment, push, email, and streaming secrets are managed centrally and never exposed in plaintext, per RFP §4.5.3. | D89: Credentials vault stores references to Secret Manager entries, not raw secrets, in the database; only Super-Admin role can view/edit; every credential rotation is audit-logged.
A90: GOV-7 | C90: Backup/restore visibility with a mandatory confirmation step so admins can verify backups are happening and recover from a bad state if needed, per RFP §4.4.2. | D90: Admin sees the timestamp of the last successful backup; triggering a restore-from-backup requires explicit Super-Admin confirmation and writes an audit-log entry; a scheduled restore drill can be configured.
A91: GOV-8 | C91: A dedicated System-health panel showing backend status, queue depths, third-party-integration health, and recent error rates, with on-call paging, per RFP §4.5.4. | D91: System-health panel (distinct from the summary widget on the general Operations Dashboard) shows live backend service status, Celery queue depth, payment/push/email/streaming integration health, and recent error-rate trend; a configurable threshold breach triggers an on-call page.
A92: SEO-1 | B92: Public Web & SEO | C92: The public website indexable by search engines so members can find JCA when they search, per RFP §3.2 and §4.1.3. | D92: Every public page has proper meta tags, Open Graph tags, and a canonical URL; an XML sitemap and robots.txt are published and correct; Google and Bing site verification is completed.
A93: SEO-2 | C93: Structured data (Schema.org) on events, religious services, and the organization so rich results can render for JCA content. | D93: Event pages emit Event schema; the organization page emits Organization/NGO schema; religious-service pages emit appropriate structured data; validated with Google's Rich Results Test.
A94: SEO-3 | C94: Public pages to meet performance budgets so search ranking and elder-device usability aren't harmed by a slow site. | D94: LCP, INP, and CLS meet 'Good' thresholds on Lighthouse for the homepage, an event page, and the donate page on a throttled mobile profile; a performance budget is enforced in CI.
A95: SEO-4 | C95: Donate and sign up for the mailing list without creating an account, per RFP §3.2. | D95: Donation and mailing-list signup flows work fully without sign-in on the public site; a post-donation prompt offers account creation without requiring it.
A96: L10N-1 | B96: Localization & Accessibility | C96: The centralized translation catalog wired end-to-end so English content renders correctly on all four surfaces from one source, per RFP §3.1 and §5.2. | D96: All user-facing strings route through the localization_string catalog; English is fully populated; a string change in the catalog reflects on all surfaces without a client redeploy (cache-invalidated).
A97: L10N-2 | C97: Hindi and Gujarati scaffolding wired (infrastructure present, not yet populated) so Phase 2 translation work has no engineering dependency. | D97: Locale switching mechanism exists and is testable end-to-end with placeholder Hindi/Gujarati strings; the full population of real translations is explicitly out of scope for this sprint and deferred to Phase 2.
A98: L10N-3 | C98: Sanskrit/Prakrit terminology and diacritics preserved verbatim in every locale so religious accuracy is never lost in translation, per RFP §5.2. | D98: Terms like anumodana, swamivatsalya, dāna, and pratikraman render identically and with correct diacritics regardless of active locale; font stack verified to render diacritics correctly on all platforms.
A99: L10N-4 | C99: A per-surface accessibility audit embedded in the Definition of Done so WCAG 2.1 AA is verified, not assumed, per RFP §4.1.1. | D99: Every shipped screen passes an automated accessibility scan plus a manual screen-reader pass (VoiceOver, TalkBack, and a desktop screen reader for web); the platform-native Skip to Content equivalents are implemented on all three surfaces; results logged per screen.
A100: L10N-5 | C100: The Payload LocalizationStrings collection to double as the translation-management screen — no separate build — so admins can manage strings without touching code. | D100: The Payload admin lists every translation key with its English value and locale variants as a standard Payload collection view; edits save immediately and propagate per L10N-1's cache-invalidation mechanism; no bespoke admin screen is built since Payload's generic collection UI already covers this.
A101: SEC-1 | B101: Security, Testing & QA | C101: TLS 1.2+ enforced everywhere with strict ATS/NSC/HSTS/CSP so all network traffic is encrypted and hardened, per RFP §5.1. | D101: All traffic redirects to TLS 1.2+; iOS App Transport Security is configured strictly with no exceptions; Android Network Security Config is strict; web enforces HSTS and a strict Content Security Policy by default.
...

Sheet Phase 2 — v1.5
A1: Phase 2 — v1.5 (should-have follow-on release)
A2: Member-gated content, governance transparency, richer educational resources. Hindi/Gujarati fully populated. RFP §4.2.
A4: ID | B4: Module | C4: User Story | D4: Description
A5: GOVD-1 | B5: Governance & Documents | C5: A membership-gated meeting-minutes archive with chronological browse, full-text search, and PDF download, per RFP §4.2. | D5: Board / Executive Committee / General Body minutes are browsable chronologically, gated to signed-in members, full-text searchable, and downloadable as PDF.
A6: GOVD-2 | C6: Upload, tag, version, redact, and publish meeting minutes with gating control, per RFP §4.2. | D6: Admin uploads a PDF, tags meeting type and date, can redact sections before publish, versions the document, and controls which membership tiers can view it.
A7: GOVD-3 | C7: Browse and search published JCA Policies so members understand the rules governing facility use, membership, and conduct, per RFP §4.2. | D7: Policies are browsable and searchable, public to members without additional gating.
A8: GOVD-4 | C8: A long-form Credits & History narrative of the Center's founding, milestones, and restoration efforts, per RFP §4.2. | D8: History page renders a CMS-authored narrative with images and a timeline component.
A9: LIB-1 | B9: Library, Jinvani & Lectures | C9: A searchable library of Jain scriptures, commentaries, and children's editions with continue-reading state, per the walkthrough's slide 26. | D9: Search covers full text of all catalog PDFs; tabs for All/Agam Sutras/Commentaries/Children/Bookmarks; a Continue Reading hero shows the last-read position (e.g. 'Tattvārtha Sūtra, p.84/312').
A10: LIB-2 | C10: Audio versions of texts like Samayika so members can listen rather than read. | D10: Audio playback available for tagged catalog entries; offline download available on mobile per RFP §4.2.
A11: LIB-3 | C11: A Pravachan (lecture) archive organized by topic, speaker, and date so members can find teachings relevant to them, per RFP §4.2. | D11: Lecture archive is browsable/filterable by topic, speaker, and date; audio/video playback with offline audio download on mobile; transcript available where uploaded.
A12: LIB-4 | C12: Browse the physical/digital library catalog, reserve a physical book, and download a licensed digital book, per RFP §4.2. | D12: Catalog distinguishes physical vs. digital availability; reservation queue for physical books; digital download respects license restrictions.
A13: LIB-5 | C13: A digital textbook library with grade-level browse, offline download, and parental controls, per RFP §4.2. | D13: Pathshala Books section is gated to enrolled families; browsable by grade level; offline download available; parental controls restrict access appropriate to the child's grade.
A14: LIB-6 | C14: Catalog management, reservation-queue handling, and license tracking for the library, plus per-grade textbook upload and download analytics for Pathshala Books, per RFP §4.2. | D14: Admin manages the full library and Pathshala Books catalogs, including upload, tagging (tradition/language/topic), reservation approval, license tracking, and download analytics.
A15: DIR-1 | B15: Directory, Travel & Facility Booking | C15: A Business Directory of member-owned Jain businesses so members can support the sangha economically, per the walkthrough's slide 27. | D15: Directory is category-filterable, shows sangha-discount tags where applicable, and lets a member list their own business for free.
A16: DIR-2 | C16: Find Jain centers and pure-veg restaurants nationwide, per the walkthrough's slide 29. | D16: Combined Centers/Restaurants/Map view lets a member find nearby centers and restaurants with Jain-friendly badges; tapping a pin opens directions in the device's maps app.
A17: DIR-3 | C17: Reserve JCA halls with member-rate pricing and see a booking-policy card, per the walkthrough's slide 28. | D17: Date picker shows the three facilities with member-rate pricing; booking-policy card (deposit percentage, refundability, pure-veg-only rule) is displayed before booking; Book routes to the shared payment-confirmation screen for the deposit.
A18: DIR-4 | C18: Approve/decline facility bookings with a calendar-conflict view and deposit tracking, per RFP §3.4 item 11. | D18: Admin sees pending booking requests with the calendar-conflict view from CAL-5 overlaid; approve/decline actions available; deposit paid/outstanding status tracked per booking.
A19: DIR-5 | C19: Approve member-submitted Business Directory and Restaurant listings so directory quality stays curated, per RFP §3.4 item 16. | D19: Submitted listings enter a review queue; approve/decline with a reason; approved listings appear live immediately.
A20: REC-1 | B20: Recognition Programs | C20: Nominate someone for a Service Award and see award recipients and ceremony info, per RFP §4.2. | D20: Nomination form is available to members; recipient list and ceremony info are publicly viewable once published.
A21: REC-2 | C21: Nomination intake and selection-committee tooling so the award process is organized and fair, per RFP §4.5. | D21: Admin sees all nominations with eligibility criteria checked; a selection-committee scoring/voting tool aggregates decisions; approved recipients publish to the member-facing recipient list.
A22: REC-3 | C22: A Lifetime Supporter Program with perpetual profile recognition and anniversary acknowledgements, per RFP §4.2. | D22: Lifetime Supporters have a distinct, perpetual public listing; anniversary acknowledgements trigger automatically on the giving anniversary date.
A23: REC-4 | C23: Recognition-rule and perpetual-listing management for the Lifetime Supporter Program, per RFP §4.5. | D23: Admin configures the qualifying threshold and rule set for Lifetime Supporter status; perpetual listings are maintained without manual re-entry each year.
A24: YTH-1 | B24: Youth & YJA | C24: A dedicated Youth section with programming, mentorship, and social events distinct from Pathshala and YJA Programs. | D24: Youth section is age-gated; content is distinct from both Pathshala (under-18 classes) and YJA Programs (18-25 national programming).
A25: YTH-2 | C25: YJA programming (events, registration links, contact info) syndicated into the app, per RFP §4.2. | D25: YJA events appear in the Calendar with a distinct YJA category; registration links route to YJA's own registration system; YJA contact info is discoverable.
A26: YTH-3 | C26: Age-gating configuration and youth-committee tools so Youth content stays appropriately scoped, per RFP §4.5. | D26: Admin configures the age-gating rule (self-attested at signup, parental consent under 18); youth-committee members get scoped access to author Youth-section content.
A27: PEG-1 | B27: Past Events & Gallery | C27: An auto-generated Past Events archive with photo links, attendance counts, and donor recognition, per RFP §4.1.2 and §4.2. | D27: Any event past its end date auto-populates into the Past Events archive with a link to its Gallery album, final attendance count, and donor-recognition summary if sponsored.
A28: PEG-2 | C28: An album-organized photo/video gallery searchable by year and event, per the walkthrough's slide 21. | D28: Hero album shows the most recent festival; album grid organized by event with a year filter; tapping an album opens a masonry grid; video albums show a play overlay.
A29: PEG-3 | C29: Curate featured entries in the auto-generated Past Events archive so the most significant events get prominence, per RFP §4.2. | D29: Admin can pin/feature specific past events above the auto-generated chronological order.
A30: RPT-1 | B30: Reports & Analytics v2 | C30: Donor cohort analysis and retention metrics so admins understand giving patterns beyond raw totals, per RFP §4.2. | D30: Report segments donors by cohort (first-year, returning, lapsed) and shows retention rate trend over time; exportable as CSV and PDF.
A31: RPT-2 | C31: A dues-aging trend report and an events chair wants an event-attendance trend report, so both roles see change over time, not just a snapshot, per RFP §4.2. | D31: Dues-aging trend shows the 30/60/90-day buckets over time; attendance trend shows RSVP and check-in rates across events over time; both exportable.
A32: RPT-3 | C32: Demographic breakdowns in reporting so program planning can be informed by who's actually participating, per RFP §4.2. | D32: Reports can break down participation by age band, family role, and tradition, respecting the privacy-by-default principle (no individually identifying data exposed in aggregate views).
A33: L10N2-1 | B33: Hindi & Gujarati Localization | C33: The full app translated into Hindi and Gujarati across every surface, per RFP §4.2 and §5.2. | D33: Every string in the localization_string catalog has a reviewed Hindi and Gujarati value; switching locale on any surface renders fully translated content with no English fallback strings remaining.
A34: L10N2-2 | C34: A reviewer workflow for translation submissions so quality is verified before a translation goes live, per RFP §5.2. | D34: A submitted translation uses Payload's draft/publish workflow to enter a pending-review state; a designated reviewer approves (publishes) or rejects with comments before it becomes the live value for that locale, built on Payload's versioning rather than a bespoke review-state machine.
A35: L10N2-3 | C35: A context-aware editing interface showing where a string appears in the app so members can translate accurately, per RFP §5.2. | D35: Translator UI shows a screenshot or screen-context preview alongside each string being translated; Sanskrit/Prakrit terms are visibly locked as non-translatable per L10N-3.
A36: HARD1-1 | B36: v1.5 Hardening & Release | C36: An updated third-party penetration test covering the v1.5 surface area so new Phase 2 features are security-verified before release, per RFP §6.1.2. | D36: Pen test covers every Phase 2 feature (gated documents, library/Jinvani, directory, facility booking, recognition programs); all High/Critical findings remediated before the Phase 2 gate.
A37: HARD1-2 | C37: Updated test coverage maintaining the v1.0 thresholds across all Phase 2 features, per RFP §6.1.2. | D37: Business-logic coverage stays >=70% including all new Phase 2 modules; E2E suite extended to cover at least one Phase 2 critical flow (e.g. gated minutes access).
A38: HARD1-3 | C38: Store updates for the v1.5 release submitted and approved on both stores, per RFP §6.1.2. | D38: iOS and Android store listings updated with new screenshots/changelog reflecting Phase 2 features; both submissions approved.

Sheet Phase 3 — v2.0
A1: Phase 3 — v2.0 (nice-to-have and contingent)
A2: Educational depth and intelligent assistance. Contingent on Phase 1 and Phase 2 acceptance gates. RFP §4.3.
A4: ID | B4: Module | C4: User Story | D4: Description
A5: PHIL-1 | B5: Jain Philosophy Module | C5: A structured, multi-lesson educational module on anekantvad, ahimsa, syadvad, the Nine Tattvas, the Five Mahavratas, the Twelve Vratas, and karma theory, per RFP §4.3. | D5: Curriculum is organized as sequential multi-lesson tracks per topic; a member can start, pause, and resume any track; content renders correctly with the diacritics/terminology rules from Phase 1.
A6: PHIL-2 | C6: Progress tracked across lessons so members can see how far they've come in their study. | D6: Progress bar per track and an overall completion percentage are visible; progress persists across sessions and devices for a signed-in member.
A7: PHIL-3 | C7: Curriculum authoring and lesson-sequencing tools plus progress analytics, per RFP §4.3. | D7: Admin can author lessons, sequence them into tracks, and view aggregate progress analytics (completion rate per track, drop-off points).
A8: CARES-1 | B8: JCA Cares | C8: See and give to JCA Cares campaigns (disaster relief, partner-organization fundraising, community outreach) so members can support causes beyond the Center itself, per RFP §4.3. | D8: JCA Cares campaigns render using the existing Cause/Donate infrastructure with a distinct visual treatment and partner-organization attribution.
A9: CARES-2 | C9: Campaign management integrated with the existing Causes tooling so JCA Cares doesn't require a parallel system, per RFP §4.3. | D9: Admin manages JCA Cares campaigns through the same Causes & Donations section used for internal causes, with an added partner-organization field.
A10: HARD2-1 | B10: v2.0 Hardening & Release | C10: A regression pass and updated pen-test scope for the v2.0 surface area (Jain Philosophy, JCA Cares) before release, per RFP §6.1.3. | D10: Full regression suite passes across all surfaces; pen-test scope extended to cover the two new Phase 3 modules; High/Critical findings remediated.
A11: HARD2-2 | C11: Store updates for the v2.0 release submitted and approved on both stores, per RFP §6.1.3. | D11: iOS and Android store listings updated reflecting v2.0 features; both submissions approved.
A12: AI-C-1 | B12: AI Chat (contingent workstream) | C12: A knowledge-base ingestion pipeline covering JCA institutional content, religious content, and FAQs so the chat has an accurate grounding corpus, per RFP §4.3. | D12: Ingestion pipeline pulls from the Library/Jinvani catalog, FAQ, policies, and admin-curated source documents into a retrieval index; a content update in the source re-indexes within a defined SLA.
A13: AI-C-2 | C13: Strict guardrails so the AI Chat never speculates on doctrine, always defers theological questions to acharyas, and cites sources for programming/factual claims, per RFP §4.3. | D13: A doctrine-classification layer detects theological questions and returns a deferral response naming how to reach an acharya, never a generated theological answer; every factual/programming claim in a response includes a source citation; a red-team test set of doctrinal edge cases passes 100%.
A14: AI-C-3 | C14: A chat interface on mobile and web so members can ask questions and get grounded answers or an escalation to staff, per RFP §4.3. | D14: Chat UI available on iOS, Android, and web; every response is either grounded with a citation, a doctrine-deferral message, or an explicit hand-off to human staff — never an unlabeled guess.
A15: AI-C-4 | C15: An escalation queue for sensitive topics and a response-audit tool so a human reviews what the AI actually says, per RFP §4.3. | D15: Any hand-off from the chat lands in an admin escalation queue with the conversation context; admins can audit any past AI response and flag it for correction or knowledge-base update.
A16: AI-C-5 | C16: A curation UI and a user-feedback loop so the AI's grounding corpus improves over time, per RFP §4.3. | D16: Admin can add, edit, or remove knowledge-base entries directly; a thumbs-up/down on any chat response feeds a feedback queue reviewed by the curator.
